COPYRIGHT
LICENSE
MANIFEST.in
mhk_loader.py
setup.py
mhk_loader.egg-info/PKG-INFO
mhk_loader.egg-info/SOURCES.txt
mhk_loader.egg-info/dependency_links.txt
mhk_loader.egg-info/requires.txt
mhk_loader.egg-info/top_level.txt