Metadata-Version: 1.1
Name: mhk-loader
Version: 0.3.0
Summary: Read tsung logs and push datas to Maheki
Home-page: https://github.com/rodo/mhk_loader
Author: Rodolphe Quiédeville
Author-email: rodolphe@quiedeville.org
License: UNKNOWN
Platform: UNKNOWN
Classifier: Development Status :: 4 - Beta
Classifier: Environment :: Web Environment
Classifier: Intended Audience :: Developers
Classifier: Intended Audience :: System Administrators
Classifier: License :: OSI Approved :: GNU General Public License v3 (GPLv3)
Classifier: Programming Language :: Python
Classifier: Operating System :: OS Independent
Classifier: Topic :: System :: Monitoring
Requires: requests
